crypto_mcp_server/__init__.py
crypto_mcp_server/binance_client.py
crypto_mcp_server/config.py
crypto_mcp_server/database.py
crypto_mcp_server/schemas.py
crypto_mcp_server/server.py
binance_mcp-3.0.1.dist-info/METADATA
binance_mcp-3.0.1.dist-info/WHEEL
binance_mcp-3.0.1.dist-info/entry_points.txt
binance_mcp-3.0.1.dist-info/top_level.txt
binance_mcp-3.0.1.dist-info/RECORD
