Metadata-Version: 2.4
Name: binance-mcp
Version: 3.0.1
Summary: MCP server for live crypto trading via Binance.US with comprehensive market intelligence, news, and advanced analytics
Author-email: Your Name <your.email@example.com>
License: MIT
Classifier: Development Status :: 4 - Beta
Classifier: Intended Audience :: Developers
Classifier: Topic :: Software Development :: Libraries :: Python Modules
Classifier: License :: OSI Approved :: MIT License
Classifier: Programming Language :: Python :: 3
Classifier: Programming Language :: Python :: 3.8
Classifier: Programming Language :: Python :: 3.9
Classifier: Programming Language :: Python :: 3.10
Classifier: Programming Language :: Python :: 3.11
Classifier: Programming Language :: Python :: 3.12
Requires-Python: >=3.8
Requires-Dist: mcp>=1.0.0
Requires-Dist: python-binance>=1.0.19
Requires-Dist: pydantic>=2.11.0
Requires-Dist: pydantic-settings>=2.5.2
Requires-Dist: python-dotenv>=1.0.0
Requires-Dist: aiohttp>=3.9.1
Requires-Dist: sqlalchemy>=2.0.25
Provides-Extra: dev
Requires-Dist: pytest>=7.4.4; extra == "dev"
Requires-Dist: pytest-asyncio>=0.23.3; extra == "dev"
